LICENSE
MANIFEST.in
README.md
setup.py
direct_speech_extractor_ru/__init__.py
direct_speech_extractor_ru/main.py
direct_speech_extractor_ru.egg-info/PKG-INFO
direct_speech_extractor_ru.egg-info/SOURCES.txt
direct_speech_extractor_ru.egg-info/dependency_links.txt
direct_speech_extractor_ru.egg-info/requires.txt
direct_speech_extractor_ru.egg-info/top_level.txt