Metadata-Version: 2.1
Name: direct-speech-extractor-ru
Version: 0.0.2
Summary: Direct speech extractor for texts in Russian
Home-page: https://github.com/diana-esaian/direct-speech-extractor-ru
Author: Diana Esaian
Author-email: diana.esaian@gmail.com
License: MIT
Classifier: License :: OSI Approved :: MIT License
Classifier: Programming Language :: Python :: 3
Classifier: Natural Language :: Russian
Classifier: Topic :: Text Processing
Requires-Python: >=3.6
License-File: LICENSE
